{
  "@context": {
    "ldp": "http://www.w3.org/ns/ldp#",
    "schema": "http://schema.org/",
    "fedora": "http://fedora.info/definitions/v4/repository#",
    "webac": "http://fedora.info/definitions/v4/webac#",
    "acl": "http://www.w3.org/ns/auth/acl#",
    "ucdlib": "http://digital.ucdavis.edu/schema#",
    "ebucore": "http://www.ebu.ch/metadata/ontologies/ebucore/ebucore#"
  },
  "@id": "",
  "@type": [
    "schema:Photograph",
    "schema:CreativeWork",
    "http://fedora.info/definitions/v4/repository#ArchivalGroup"
  ],
  "schema:about": [
    {
      "@id": "http://id.worldcat.org/fast/938950"
    },
    {
      "@id": "http://id.worldcat.org/fast/815177"
    },
    {
      "@id": "http://id.worldcat.org/fast/1155984"
    },
    {
      "@id": "http://id.worldcat.org/fast/1109483"
    },
    {
      "@id": "http://id.worldcat.org/fast/1118336"
    }
  ],
  "schema:associatedMedia": {
    "@id": "@base:/B-5593.tif"
  },
  "schema:creator": [
    {
      "@id": "http://id.loc.gov/authorities/names/no2014099630",
      "schema:name": "Eastman, Jervie Henry"
    }
  ],
  "schema:datePublished": {
    "@type": "http://www.w3.org/2001/XMLSchema#date",
    "@value": "1947"
  },
  "schema:description": "Monument with statue, sign on railing reading \"Please Remain Outside of Railing James W. Marshall Lies Buried Here,\" sign mounted on stone gate post reading \"DOGS MUST BE KEPT ON LEASH, and trees in background.",
  "schema:identifier": [
    "B-5593",
    "ark:/13030/tf4h4nb0zs"
  ],
  "schema:keywords": [
    "Sculpture",
    "Gates",
    "Signs",
    "Art",
    "Trees",
    "Railings",
    "Monuments & memorials"
  ],
  "schema:license": {
    "@id": "http://rightsstatements.org/vocab/InC-NC/1.0/"
  },
  "schema:material": "1 photographic negative : b&w : 5 x 7 in.",
  "schema:name": "The Marshall Monument at Coloma, Calif",
  "schema:publisher": [
    {
      "@id": "http://id.loc.gov/authorities/names/no2008108707",
      "schema:name": "University of California, Davis. General Library. Dept. of Special Collections"
    }
  ]
}
