{
  "@context": {
    "ldp": "http://www.w3.org/ns/ldp#",
    "schema": "http://schema.org/",
    "fedora": "http://fedora.info/definitions/v4/repository#",
    "webac": "http://fedora.info/definitions/v4/webac#",
    "acl": "http://www.w3.org/ns/auth/acl#",
    "ucdlib": "http://digital.ucdavis.edu/schema#",
    "ebucore": "http://www.ebu.ch/metadata/ontologies/ebucore/ebucore#"
  },
  "@id": "",
  "@type": [
    "schema:CreativeWork",
    "schema:Photograph",
    "http://fedora.info/definitions/v4/repository#ArchivalGroup"
  ],
  "schema:about": [
    {
      "@id": "http://id.worldcat.org/fast/1092327"
    },
    {
      "@id": "http://id.worldcat.org/fast/923012"
    },
    {
      "@id": "http://id.worldcat.org/fast/854835"
    },
    {
      "@id": "http://id.worldcat.org/fast/1155984"
    },
    {
      "@id": "http://id.worldcat.org/fast/1176568"
    },
    {
      "@id": "http://id.worldcat.org/fast/1065823"
    }
  ],
  "schema:associatedMedia": {
    "@id": "@base:/media/B-6928.tif"
  },
  "schema:creator": [
    {
      "@id": "http://id.loc.gov/authorities/names/no2014099630"
    },
    "Eastman, Jervie Henry"
  ],
  "schema:datePublished": {
    "@type": "http://www.w3.org/2001/XMLSchema#date",
    "@value": "1949"
  },
  "schema:description": "Woman and girl standing in forest surrounded by ferns and redwood trees. Caption on cellophane reads \"Giant Ferns along the Redwood Highway, Calif.\"",
  "schema:identifier": [
    "B-6928",
    "ark:/13030/tf8n39p20v"
  ],
  "schema:isPartOf": {
    "@id": "https://oac.cdlib.org/findaid/ark:/13030/tf6w100646/"
  },
  "schema:keywords": [
    "Women",
    "Ferns",
    "Trees",
    "People",
    "Redwoods",
    "Plants",
    "Children"
  ],
  "schema:license": {
    "@id": "http://rightsstatements.org/vocab/InC-NC/1.0/"
  },
  "schema:material": "1 photographic negative : b&w : 5 x 7 in.",
  "schema:name": "Giant Ferns among the Redwoods",
  "schema:publisher": [
    "University of California, Davis. General Library. Dept. of Special Collections",
    {
      "@id": "http://id.loc.gov/authorities/names/no2008108707"
    }
  ]
}